{
  "users": [
    {
      "email": "test@test.com",
      "password": "$2a$10$UIweiOYMCNvjoSnv6Ndn2uaMfICGvpZG3vceocdUf7V2ABAhx.yJK",
      "name": "test",
      "id": 2
    },
    {
      "email": "husam@husam.com",
      "password": "$2a$10$DYflnJnsToD1PKJWHIIIg.QZqE/h4YjlMWyncpd9kYeFcCbisS4Gy",
      "name": "fxgdfg",
      "id": 3
    }
  ],
  "products": [
    {
      "id": 1,
      "title": "iPhone 11 64GB",
      "description": "The iPhone 11 was introduced in September 2019, and Apple has continued selling it as a lower-priced option alongside subsequent iPhone generations, with the launch of the iPhone 13 lineup. The iPhone 11 features a 6.1-inch display, a dual-lens camera, and an A13 Bionic chip. ",
      "price": 399.99,
      "Stock": 10,
      "brand": "Apple",
      "category": "Smartphones",
      "thumbnails": [
        "/assets/images/product/iPhone-11-128GB/IPhone11-1.jpg",
        "/assets/images/product/iPhone-11-128GB/IPhone11-2.jpg",
        "/assets/images/product/iPhone-11-128GB/IPhone11-3.jpg"
      ]
    },
    {
      "id": 2,
      "title": "iPhone 12 Mini 64G",
      "description": "The Apple iPhone 12 mini (64GB) is a good iOS phone with 3.1GHz Hexa-core processor that allows run games and heavy applications With one SIM card slot, the Apple iPhone 12 mini (64GB) allows download up to 5000 Mbps for internet browsing, but it also depends on the carrier. ",
      "price": 325,
      "Stock": 30,
      "brand": "Apple",
      "category": "Smartphones",
      "thumbnails": [
        "/assets/images/product/iPhone_12_Mini/IPhone12Mini-1.jpg",
        "/assets/images/product/iPhone_12_Mini/IPhone12Mini-2.jpg",
        "/assets/images/product/iPhone_12_Mini/IPhone12Mini-3.jpg"
      ]
    },
    {
      "id": 3,
      "title": "iPhone 13 mini 128G",
      "description": "The Apple iPhone 13 mini (128GB) is a good iOS phone with 3.23GHz Hexa-core processor that allows run games and heavy applications       With one SIM card slot, the Apple iPhone 13 mini (128GB) allows download up to 5000 Mbps for internet browsing, but it also depends on the carrier.",
      "price": 559,
      "Stock": 20,
      "brand": "Apple",
      "category": "Smartphones",
      "thumbnails": [
        "/assets/images/product/iPhone_13_mini/IPhone13Mini-1.jpg",
        "/assets/images/product/iPhone_13_mini/IPhone13Mini-2.jpg",
        "/assets/images/product/iPhone_13_mini/IPhone13Mini-3.jpg"
      ]
    },
    {
      "id": 4,
      "title": "iPhone 13 Pro Max 128G",
      "description": "The Apple iPhone 13 Pro Max (128GB) is a good iOS phone with 3.23GHz Hexa-core processor that allows run games and heavy applications With one SIM card slot, the Apple iPhone 13 Pro Max (128GB) allows download up to 5000 Mbps for internet browsing, but it also depends on the carrier.",
      "price": 997.46,
      "Stock": 30,
      "brand": "Apple",
      "category": "Smartphones",
      "thumbnails": [
        "/assets/images/product/iPhone-13-Pro-Max/IPhone13ProMax-1.jpg",
        "/assets/images/product/iPhone-13-Pro-Max/IPhone13ProMax-2.jpg",
        "/assets/images/product/iPhone-13-Pro-Max/IPhone13ProMax-3.jpg"
      ]
    },
    {
      "id": 5,
      "title": "iPhone X 64GB",
      "description": "The Apple iPhone X (64GB) is a good iOS phone with 2.39GHz Hexa-core processor that allows run games and heavy applications With one SIM card slot, the Apple iPhone X (64GB) allows download up to 1024 Mbps for internet browsing, but it also depends on the carrier.",
      "price": 199,
      "Stock": 15,
      "brand": "Apple",
      "category": "Smartphones",
      "thumbnails": [
        "/assets/images/product/iPhone-X/IphoneX-1.jpg",
        "/assets/images/product/iPhone-X/IphoneX-2.jpg",
        "/assets/images/product/iPhone-X/IphoneX-3.jpg"
      ]
    },
    {
      "id": 6,
      "title": "iPhone 14 Pro Max 128G",
      "description": " The Apple iPhone 14 Pro Max (128GB) is a good iOS phone with 3.46GHz Hexa-core processor that allows run games and heavy applications.       Great connectivity of this device includes Bluetooth 5.3 + A2DP/LE, WiFi 802.11 a/b/g/n/ac/ax [wifi6] (2.4GHz, 5GHz) + MIMO and NFC to make mobile payments or connection to other devices.",
      "price": 1099,
      "Stock": 30,
      "brand": "Apple",
      "category": "Smartphones",
      "thumbnails": [
        "/assets/images/product/iPhone-14-ProMax/IPhone14ProMax-1.jpg",
        "/assets/images/product/iPhone-14-ProMax/IPhone14ProMax-2.jpg",
        "/assets/images/product/iPhone-14-ProMax/IPhone14ProMax-3.jpg"
      ]
    },
    {
      "id": 7,
      "title": "Samsung A32 4ram 128G",
      "description": "The Samsung Galaxy A32 (SM-A325F/DS 128GB/4GB) is a good Android phone with 2GHz Octa-core processor that allows run games and heavy applications An advantage of the Samsung Galaxy A32 (SM-A325F/DS 128GB/4GB) is the possibility of using two mobile carriers, a Dual-SIM device with two SIM card slots.",
      "price": 279.99,
      "Stock": 30,
      "brand": "Samsung",
      "category": "Smartphones",
      "thumbnails": [
        "/assets/images/product/Samsung-Galaxy-A32/Samsung-A32-1.jpg",
        "/assets/images/product/Samsung-Galaxy-A32/Samsung-A32-2.jpg",
        "/assets/images/product/Samsung-Galaxy-A32/Samsung-A32-3.jpg"
      ]
    },
    {
      "id": 8,
      "title": "samsung A53 5G",
      "description": "The Samsung Galaxy A53 (SM-A5360 256GB) is a good Android phone with 2.4GHz Octa-core processor that allows run games and heavy applications       An advantage of the Samsung Galaxy A53 (SM-A5360 256GB) is the possibility of using two mobile carriers, a Dual-SIM device with two SIM card slots.",
      "price": 325,
      "Stock": 30,
      "brand": "Samsung",
      "category": "Smartphones",
      "thumbnails": [
        "/assets/images/product/Galaxy-A53/GalaxyA53-1.jpg",
        "/assets/images/product/Galaxy-A53/GalaxyA53-2.jpg",
        "/assets/images/product/Galaxy-A53/GalaxyA53-3.jpg"
      ]
    },
    {
      "id": 9,
      "title": "samsung galaxy z fold4 5g",
      "description": "The Samsung Galaxy Z Fold 4 (SM-F936U 1TB) is a good Android phone with 3.19GHz Octa-core processor that allows run games and heavy applications       With one SIM card slot, the Samsung Galaxy Z Fold 4 (SM-F936U 1TB) allows download up to 5000 Mbps for internet browsing, but it also depends on the carrier.",
      "price": 1230,
      "Stock": 20,
      "brand": "Samsung",
      "category": "Smartphones",
      "thumbnails": [
        "/assets/images/product/samsung-galaxy-z/SamsungGalaxyZ-1.jpg",
        "/assets/images/product/samsung-galaxy-z/SamsungGalaxyZ-2.jpg",
        "/assets/images/product/samsung-galaxy-z/SamsungGalaxyZ-3.jpg"
      ]
    },
    {
      "id": 10,
      "title": "Rockerz 450 Pro Headphone",
      "description": "boAt Rockerz 450 Pro | Wireless Headphone with 40mm Massive Drivers, Mountainous Playback Upto 70 Hours, Asap Chargee, Noise cancelling is good for the price, and optional wired listening is handy.      ",
      "price": 41,
      "Stock": 20,
      "brand": "Rockerz",
      "category": "Headphones",
      "thumbnails": [
        "/assets/images/product/Rockerz-450-Pro/Rockerz450Pro-1.jpg",
        "/assets/images/product/Rockerz-450-Pro/Rockerz450Pro-2.jpg",
        "/assets/images/product/Rockerz-450-Pro/Rockerz450Pro-3.jpg"
      ]
    },
    {
      "id": 11,
      "title": "dbE HBT80 Headphone",
      "description": "dbE HBT80 Wireless Bluetooth Headset HBT 80 Wireless Headphone It is light in weight and easy to use, Noise cancelling is good for the price, and optional wired listening is handy.      ",
      "price": 30,
      "Stock": 25,
      "brand": "dbE",
      "category": "Headphones",
      "thumbnails": [
        "/assets/images/product/HBT80Headphone/HBT80Headphone-1.jpg",
        "/assets/images/product/HBT80Headphone/HBT80Headphone-2.jpg",
        "/assets/images/product/HBT80Headphone/HBT80Headphone-3.jpg"
      ]
    },
    {
      "id": 12,
      "title": "Sony WH-XB910N Extra Headphone",
      "description": "The WH-XB910N noise cancelling headphones enhance all your low-end frequencies for exceptional bass Yet these wireless headphones also maintain vocal clarity for a wonderfully rich, well-rounded listening experience. ",
      "price": 248,
      "Stock": 30,
      "brand": "Sony",
      "category": "Headphones",
      "thumbnails": [
        "/assets/images/product/Sony-WH-XB910N/Sony-WH-XB910N-1.jpg",
        "/assets/images/product/Sony-WH-XB910N/Sony-WH-XB910N-2.jpg",
        "/assets/images/product/Sony-WH-XB910N/Sony-WH-XB910N-3.jpg"
      ]
    },
    {
      "id": 13,
      "title": "Beats Solo3 Wireless Headphone",
      "description": "      High-performance wireless Bluetooth headphones, Features the Apple W1 chip and Class 1 wireless Bluetooth connectivity With up to 40 hours of battery life, Compatible with iOS and Android devices.",
      "price": 158,
      "Stock": 30,
      "brand": "Beats",
      "category": "Headphones",
      "thumbnails": [
        "/assets/images/product/Beats-Solo3/Beats-Solo3-1.jpg",
        "/assets/images/product/Beats-Solo3/Beats-Solo3-2.jpg",
        "/assets/images/product/Beats-Solo3/Beats-Solo3-3.jpg"
      ]
    },
    {
      "id": 14,
      "title": "W20 TWS Earphone Headphone",
      "description": "Picun W20 True Wireless Earbuds 36 Hours Playtime Bluetooth 5.0+EDR HiFi Crystal Bass IPX8 Waterproof in-Ear Headphones w/HD Mic, Touch Control, Hall Switch, USB-C, Single/Twin Mode Comfy for Sports     ",
      "price": 26,
      "Stock": 30,
      "brand": "Picun",
      "category": "Headphones",
      "thumbnails": [
        "/assets/images/product/W20-TWS-Earphone/W20-TWS-Earphone-1.jpg",
        "/assets/images/product/W20-TWS-Earphone/W20-TWS-Earphone-2.jpg",
        "/assets/images/product/W20-TWS-Earphone/W20-TWS-Earphone-3.jpg"
      ]
    }
  ],
  "reviews": [
    {
      "rating": 4,
      "feedback": "Thank you good product And excellent delivery",
      "productId": 1,
      "id": 4
    },
    {
      "rating": 3,
      "feedback": "The type of guarantee is local or international",
      "productId": 1,
      "id": 1
    },
    {
      "rating": 3,
      "feedback": "The iPhone is well known",
      "productId": 2,
      "id": 1
    },
    {
      "rating": 5,
      "feedback": "Superb With excellent battery performance",
      "productId": 3,
      "id": 2
    },
    {
      "rating": 5,
      "feedback": "Original product, as described, helpful and respectful seller",
      "productId": 4,
      "id": 9
    },
    {
      "rating": 5,
      "feedback": "I'm great at everything!",
      "productId": 4,
      "id": 10
    },
    {
      "rating": 2,
      "feedback": "The price is high",
      "productId": 5,
      "id": 3
    },
    {
      "rating": 4,
      "feedback": "Goode product",
      "productId": 5,
      "id": 4
    },
    {
      "rating": 4,
      "feedback": "Really solid phone, although not very different from iphone 13, the battery life is very good",
      "productId": 6,
      "id": 4
    },
    {
      "rating": 4,
      "feedback": "Thank you good product And excellent delivery",
      "productId": 6,
      "id": 4
    },
    {
      "rating": 4,
      "feedback": "The product is a amazin",
      "productId": 8,
      "id": 8
    },
    {
      "rating": 5,
      "feedback": "Bought it for a friend, who appears to be delighted with it.",
      "productId": 8,
      "id": 11
    },
    {
      "rating": 5,
      "feedback": "Very excellent device",
      "productId": 8,
      "id": 5
    },
    {
      "rating": 5,
      "feedback": "The product is a amazing",
      "productId": 8,
      "id": 6
    },
    {
      "rating": 5,
      "feedback": "The product is beautiful and original + the prices are original without increasing the same original initial prices without increasing as is the case in a market of astronomical amounts",
      "productId": 8,
      "id": 7
    },
    {
      "rating": 4,
      "feedback": "The speed of delivery is the iPhone is easy to use and its capabilities are very good",
      "productId": 8,
      "id": 12
    },
    {
      "rating": 2,
      "feedback": "I have not received the purchase invoice for the phone. How do I receive this bill?",
      "productId": 8,
      "id": 13
    },
    {
      "rating": 2,
      "feedback": "Not recommended at all",
      "productId": 8,
      "id": 13
    },
    {
      "rating": 5,
      "feedback": "Awesome I really like it",
      "productId": 8,
      "id": 19
    },
    {
      "rating": 5,
      "feedback": "It does not need, original and approved suspension, and a two-year warranty",
      "productId": 8,
      "id": 21
    },
    {
      "rating": 5,
      "feedback": "Excellent, great, but big",
      "productId": 9,
      "id": 17
    },
    {
      "rating": 5,
      "feedback": "Its price is very excellent and 100% original 👍🏻",
      "productId": 9,
      "id": 18
    },
    {
      "rating": 5,
      "feedback": "Very beautiful, fast delivery from the market, the product is great, the packaging is very good, and the original has not been used",
      "productId": 9,
      "id": 22
    },
    {
      "rating": 4,
      "feedback": "Good product",
      "productId": 10,
      "id": 17
    },
    {
      "rating": 5,
      "feedback": "Standard time for delivery",
      "productId": 12,
      "id": 20
    },
    {
      "rating": 5,
      "feedback": "Perfekt zum Abschalten und fokussieren",
      "productId": 13,
      "id": 20
    },
    {
      "rating": 4,
      "feedback": "Conforme à mes attentes.",
      "productId": 13,
      "id": 20
    },
    {
      "rating": 5,
      "feedback": "Original",
      "productId": 14,
      "id": 16
    },
    {
      "rating": 5,
      "feedback": "Great. Great. ",
      "productId": 14,
      "id": 14
    },
    {
      "rating": 4,
      "feedback": "Good",
      "productId": 14,
      "id": 15
    }
  ],
  "orders": [
    {
      "orderItems": [
        {
          "id": 5,
          "title": "iPhone X 64GB",
          "price": 199,
          "image": "/assets/images/product/iPhone-X/IphoneX-1.jpg",
          "Stock": 15,
          "quantity": 1,
          "products": 5
        }
      ],
      "shippingAddress": {
        "country": "palstane ",
        "city": "gaza",
        "address": "gaza",
        "postalCode": "000000"
      },
      "totalPrice": "199.00",
      "createdAt": "9/10/2023",
      "id": 22
    }
  ]
}